_foo.cpython-38-x86_64-linux-gnu.so
tensorflow_onmttok_ops-0.4.0.dist-info/top_level.txt
tensorflow_onmttok_ops-0.4.0.dist-info/RECORD
tensorflow_onmttok_ops-0.4.0.dist-info/METADATA
tensorflow_onmttok_ops-0.4.0.dist-info/LICENSE
tensorflow_onmttok_ops-0.4.0.dist-info/WHEEL
tensorflow_onmttok/__init__.py
tensorflow_onmttok/python/__init__.py
tensorflow_onmttok/python/ops/onmttok_ops.py
tensorflow_onmttok/python/ops/_tensorflow_onmttok_ops.so
tensorflow_onmttok/python/ops/__init__.py
tensorflow_onmttok/python/opennmt/opennmt_in_graph_tokenizer.py
tensorflow_onmttok/python/opennmt/__init__.py
