Metadata-Version: 2.1
Name: tensorflow-onmttok-ops
Version: 0.4.0
Summary: OpenNMT Tokenizer as TensorFlow Operations
Home-page: https://github.com/eohana/tensorflow-onmttok-ops
Author: Emmanuel Ohana
Author-email: manu.ohana@gmail.com
License: Apache 2.0
Keywords: tensorflow opennmt tokenizer
Platform: UNKNOWN
Classifier: Development Status :: 4 - Beta
Classifier: Intended Audience :: Developers
Classifier: Intended Audience :: Education
Classifier: Intended Audience :: Science/Research
Classifier: License :: OSI Approved :: Apache Software License
Classifier: Programming Language :: Python :: 3.5
Classifier: Programming Language :: Python :: 3.6
Classifier: Programming Language :: Python :: 3.7
Classifier: Topic :: Software Development :: Libraries :: Python Modules
Classifier: Topic :: Software Development :: Libraries
Requires-Dist: tensorflow (<2.3,>=2.1)
